Metadata-Version: 2.4
Name: adafruit-circuitpython-monsterm4sk
Version: 1.0.7
Summary: Helper library for the MONSTER M4SK device. Allows usage of screens and other built-in hardware.
Author-email: Adafruit Industries <circuitpython@adafruit.com>
License: MIT
Project-URL: Homepage, https://github.com/adafruit/Adafruit_CircuitPython_MONSTERM4SK
Keywords: adafruit,monsterm4sk,microcontroller,display,breakout,hardwaremicropython,circuitpython
Classifier: Intended Audience :: Developers
Classifier: Topic :: Software Development :: Libraries
Classifier: Topic :: Software Development :: Embedded Systems
Classifier: Topic :: System :: Hardware
Classifier: License :: OSI Approved :: MIT License
Classifier: Programming Language :: Python :: 3
License-File: LICENSE
Requires-Dist: Adafruit-Blinka
Requires-Dist: adafruit-circuitpython-busdevice
Requires-Dist: adafruit-circuitpython-st7789
Requires-Dist: adafruit-circuitpython-register
Requires-Dist: adafruit-circuitpython-lis3dh
Requires-Dist: adafruit-circuitpython-seesaw
Provides-Extra: optional
Dynamic: license-file
